<?xml version="1.0" encoding="utf-8"?> 
<product version="1.5" xmlns:xsi="http://www.w3.org/2001/XMLSchema-instance" xsi:noNamespaceSchemaLocation="http://www.bom.gov.au/schema/v1.5/product.xsd"><amoc><source><sender>Australian Government Bureau of Meteorology</sender><region>Northern Territory</region><office>NTRO</office><copyright>http://www.bom.gov.au/other/copyright.shtml</copyright><disclaimer>http://www.bom.gov.au/other/disclaimer.shtml</disclaimer></source><identifier>IDD10204</identifier><issue-time-utc>2016-03-18T20:00:00Z</issue-time-utc><issue-time-local tz="CST">2016-03-19T05:30:00+09:30</issue-time-local><sent-time>2016-03-18T20:01:49Z</sent-time><expiry-time>2016-03-19T20:00:00Z</expiry-time><validity-bgn-time-local tz="CST">2016-03-19T00:00:00+09:30</validity-bgn-time-local><validity-end-time-local tz="CST">2016-03-25T23:59:59+09:30</validity-end-time-local><next-routine-issue-time-utc>2016-03-19T07:00:00Z</next-routine-issue-time-utc><next-routine-issue-time-local tz="CST">2016-03-19T16:30:00+09:30</next-routine-issue-time-local><status>O</status><service>WSP</service><sub-service>FTW</sub-service><product-type>F</product-type><phase>NEW</phase></amoc><forecast><area aac="NT_FA001" description="Northern Territory" type="region"><forecast-period start-time-local="2016-03-19T05:31:49+09:30" end-time-local="2016-03-19T05:31:49+09:30" start-time-utc="2016-03-18T20:01:49Z" end-time-utc="2016-03-18T20:01:49Z"><text type="warning_summary_footer">For latest warnings go to www.bom.gov.au, subscribe to RSS feeds, call 1300 659 214* or listen for warnings on relevant TV and radio broadcasts.</text><text type="product_footer">* Calls to 1300 numbers cost around 27.5c inc GST, higher from mobiles or public phones.</text></forecast-period></area><area aac="NT_PT011" description="Wadeye" type="location" parent-aac="NT_FA001"><forecast-period index="0" start-time-local="2016-03-19T00:00:00+09:30" end-time-local="2016-03-20T00:00:00+09:30" start-time-utc="2016-03-18T14:30:00Z" end-time-utc="2016-03-19T14:30:00Z"><element type="forecast_icon_code">16</element><element type="air_temperature_maximum" units="Celsius">34</element><text type="forecast">Partly cloudy. Medium (50%) chance of showers, most likely during this afternoon and evening. The chance of a thunderstorm during this afternoon and evening with gusty winds. Light winds becoming westerly 15 to 20 km/h in the early afternoon then becoming light in the late afternoon.</text><text type="precis">Shower or two. Possible storm.</text><text type="probability_of_precipitation">50%</text><text type="fire_danger">Low-Moderate</text><text type="uv_alert">UV Alert from 9:20 am to 4:40 pm, UV Index predicted to reach 14 [Extreme]</text></forecast-period><forecast-period index="1" start-time-local="2016-03-20T00:00:00+09:30" end-time-local="2016-03-21T00:00:00+09:30" start-time-utc="2016-03-19T14:30:00Z" end-time-utc="2016-03-20T14:30:00Z"><element type="forecast_icon_code">16</element><element type="precipitation_range">0 to 4 mm</element><element type="air_temperature_minimum" units="Celsius">26</element><element type="air_temperature_maximum" units="Celsius">35</element><text type="forecast">Partly cloudy. Medium (50%) chance of showers, most likely in the late morning and afternoon. The chance of a thunderstorm in the late morning and afternoon. Light winds.</text><text type="precis">Shower or two. Possible storm.</text><text type="probability_of_precipitation">50%</text></forecast-period><forecast-period index="2" start-time-local="2016-03-21T00:00:00+09:30" end-time-local="2016-03-22T00:00:00+09:30" start-time-utc="2016-03-20T14:30:00Z" end-time-utc="2016-03-21T14:30:00Z"><element type="forecast_icon_code">16</element><element type="precipitation_range">0 to 3 mm</element><element type="air_temperature_minimum" units="Celsius">26</element><element type="air_temperature_maximum" units="Celsius">35</element><text type="forecast">Partly cloudy. Medium (40%) chance of showers in the morning and afternoon. The chance of a thunderstorm in the morning and afternoon. Light winds.</text><text type="precis">Possible shower or storm.</text><text type="probability_of_precipitation">40%</text></forecast-period><forecast-period index="3" start-time-local="2016-03-22T00:00:00+09:30" end-time-local="2016-03-23T00:00:00+09:30" start-time-utc="2016-03-21T14:30:00Z" end-time-utc="2016-03-22T14:30:00Z"><element type="forecast_icon_code">16</element><element type="precipitation_range">0 to 3 mm</element><element type="air_temperature_minimum" units="Celsius">26</element><element type="air_temperature_maximum" units="Celsius">35</element><text type="forecast">Mostly sunny. Medium (40%) chance of showers in the morning and afternoon. The chance of a thunderstorm in the morning and afternoon. Light winds.</text><text type="precis">Possible shower or storm.</text><text type="probability_of_precipitation">40%</text></forecast-period><forecast-period index="4" start-time-local="2016-03-23T00:00:00+09:30" end-time-local="2016-03-24T00:00:00+09:30" start-time-utc="2016-03-22T14:30:00Z" end-time-utc="2016-03-23T14:30:00Z"><element type="forecast_icon_code">16</element><element type="precipitation_range">0 to 0.2 mm</element><element type="air_temperature_minimum" units="Celsius">27</element><element type="air_temperature_maximum" units="Celsius">36</element><text type="forecast">Mostly sunny. Slight (20%) chance of a shower. The chance of a thunderstorm. Light winds.</text><text type="precis">Possible storm.</text><text type="probability_of_precipitation">20%</text></forecast-period><forecast-period index="5" start-time-local="2016-03-24T00:00:00+09:30" end-time-local="2016-03-25T00:00:00+09:30" start-time-utc="2016-03-23T14:30:00Z" end-time-utc="2016-03-24T14:30:00Z"><element type="forecast_icon_code">3</element><element type="precipitation_range">0 mm</element><element type="air_temperature_minimum" units="Celsius">27</element><element type="air_temperature_maximum" units="Celsius">36</element><text type="forecast">Partly cloudy. Slight (20%) chance of a shower. The chance of a thunderstorm. Light winds.</text><text type="precis">Partly cloudy.</text><text type="probability_of_precipitation">20%</text></forecast-period><forecast-period index="6" start-time-local="2016-03-25T00:00:00+09:30" end-time-local="2016-03-26T00:00:00+09:30" start-time-utc="2016-03-24T14:30:00Z" end-time-utc="2016-03-25T14:30:00Z"><element type="forecast_icon_code">16</element><element type="precipitation_range">0 to 1 mm</element><element type="air_temperature_minimum" units="Celsius">26</element><element type="air_temperature_maximum" units="Celsius">35</element><text type="forecast">Partly cloudy. Slight (30%) chance of a shower. The chance of a thunderstorm. Light winds.</text><text type="precis">Possible shower or storm.</text><text type="probability_of_precipitation">30%</text></forecast-period></area></forecast></product>
