<?xml version="1.0" encoding="utf-8"?> 
<!DOCTYPE weather-observations SYSTEM "http://www.bom.gov.au/dtd/weather-observations.dtd" [<!ENTITY degree "&#176;"> ]><weather-observations><product id="IDT65013" name="Current Weather Details for Tasmania" title="Current Weather Details for Tasmania" create-time-local="20160319T1539" create-time-utc="20160319T0439" time-zone="EDT"><head><copyright-notice owner="Bureau of Meteorology, Australia" year="2016"><text>		#-------------------------------------------					Please note the					&lt;a href="http://www.bom.gov.au/other/copyright.shtml"&gt;Copyright Notice and Disclaimer&lt;/a&gt;					relating to the use of the information. 					Users of this information are deemed to have read and accepted the					conditions described in the					&lt;a href="http://www.bom.gov.au/other/copyright.shtml"&gt;Copyright Notice and Disclaimer&lt;/a&gt;				</text></copyright-notice><issuing-office>				Bureau of Meteorology, Tasmania and Antarctica Regional Office, Hobart, Tasmania, Australia			</issuing-office></head><group name="current"><obs-def obs-time-local="20160319T1539" obs-time-utc="20160319T0439" time-zone="EDT"><data-def type="at" name="temperature" unit="celsius" unit-abbreviation="&#176;C" /><data-def type="dp" name="dewpoint" unit="celsius" unit-abbreviation="&#176;C" /><data-def type="rh" name="relative humidity" unit="percent" unit-abbreviation="%" /><data-def type="wd" name="wind direction" unit="compass points" unit-abbreviation="" /><data-def type="wskm" name="wind speed" unit="kilometres per hour" unit-abbreviation="km/h" /><data-def type="wskt" name="wind speed" unit="knots" unit-abbreviation="kt" /><data-def type="wgkm" name="wind gust" unit="kilometres per hour" unit-abbreviation="km/h" /><data-def type="wgkt" name="wind gust" unit="knots" unit-abbreviation="kt" /><data-def type="mslp" name="msl pressure" unit="hectopascals" unit-abbreviation="hPa" /><data-def type="r9" name="rain since 9am" unit="millimetres" unit-abbreviation="mm" /><data-def type="ss" name="sea state" unit="metres" unit-abbreviation="m" /><data-def type="sws" name="swell state" unit="metres" unit-abbreviation="m" /></obs-def><obs obs-time-local="20160319T1000" obs-time-utc="20160318T2300" time-zone="EDT" site ="092003" wmo="95989" station="Bicheno" source="SYNOP" locale-type="locality" locale-num="" locale=""><d t="at">12.5</d><d t="dp">4.7</d><d t="rh">59</d><d t="wd">SSE</d><d t="wskm">33</d><d t="wskt">18</d><d t="r9">0.0</d></obs><obs obs-time-local="20160319T1500" obs-time-utc="20160319T0400" time-zone="EDT" site ="091284" wmo="95973" station="Bridport" source="SYNOP" locale-type="locality" locale-num="" locale=""><d t="at">19.0</d><d t="dp">5.0</d><d t="rh">40</d><d t="wd">E</d><d t="wskm">7</d><d t="wskt">4</d><d t="r9">0.0</d></obs><obs obs-time-local="20160319T1500" obs-time-utc="20160319T0400" time-zone="EDT" site ="091009" wmo="94958" station="Burnie" source="SYNOP" locale-type="locality" locale-num="" locale=""><d t="at">17.8</d><d t="dp">15.6</d><d t="rh">87</d><d t="wd">SW</d><d t="wskm">9</d><d t="wskt">5</d><d t="r9">0.0</d><d t="ss">&lt;0.5</d><d t="sws">&lt;2</d></obs><obs obs-time-local="20160319T1530" obs-time-utc="20160319T0430" time-zone="EDT" site ="095003" wmo="94964" station="Bushy Park" source="METAR" locale-type="locality" locale-num="" locale=""><d t="at">15.3</d><d t="dp">1.8</d><d t="rh">40</d><d t="wd">S</d><d t="wskm">24</d><d t="wskt">13</d><d t="wgkm">30</d><d t="wgkt">16</d><d t="r9">0.0</d></obs><obs obs-time-local="20160319T1500" obs-time-utc="20160319T0400" time-zone="EDT" site ="094212" wmo="95972" station="Campania" source="SYNOP" locale-type="locality" locale-num="" locale=""><d t="at">15.5</d><d t="dp">3.3</d><d t="rh">44</d><d t="wd">SSW</d><d t="wskm">24</d><d t="wskt">13</d><d t="r9">0.0</d></obs><obs obs-time-local="20160319T1530" obs-time-utc="20160319T0430" time-zone="EDT" site ="091245" wmo="94954" station="Cape Grim" source="METAR" locale-type="locality" locale-num="" locale=""><d t="at">14.2</d><d t="dp">4.2</d><d t="rh">51</d><d t="wd">S</d><d t="wskm">44</d><d t="wskt">24</d><d t="wgkm">56</d><d t="wgkt">30</d><d t="mslp">1016.8</d><d t="r9">0.0</d></obs><obs obs-time-local="20160319T1500" obs-time-utc="20160319T0400" time-zone="EDT" site ="097000" wmo="94974" station="Cape Sorell" source="SYNOP" locale-type="locality" locale-num="" locale=""><d t="at">14.1</d><d t="dp">7.6</d><d t="rh">65</d><d t="wd">S</d><d t="wskm">35</d><d t="wskt">19</d><d t="mslp">1017.0</d><d t="r9">0.0</d></obs><obs obs-time-local="20160319T1500" obs-time-utc="20160319T0400" time-zone="EDT" site ="091331" wmo="95954" station="Cradle Mt AP" source="SYNOP" locale-type="locality" locale-num="" locale=""><d t="at">14.1</d><d t="dp">6.0</d><d t="rh">58</d><d t="wd">SSW</d><d t="wskm">37</d><d t="wskt">20</d><d t="mslp">1016.5</d><d t="r9">0.0</d></obs><obs obs-time-local="20160319T1530" obs-time-utc="20160319T0430" time-zone="EDT" site ="091306" wmo="95969" station="Cressy" source="METAR" locale-type="locality" locale-num="" locale=""><d t="at">16.8</d><d t="dp">5.1</d><d t="rh">46</d><d t="wd">SSE</d><d t="wskm">20</d><d t="wskt">11</d><d t="wgkm">30</d><d t="wgkt">16</d><d t="r9">0.0</d></obs><obs obs-time-local="20160319T1530" obs-time-utc="20160319T0430" time-zone="EDT" site ="091126" wmo="95960" station="Devonport" source="METAR" locale-type="locality" locale-num="" locale=""><d t="at">18.4</d><d t="dp">5.3</d><d t="rh">42</d><d t="wd">ESE</d><d t="wskm">13</d><d t="wskt">7</d><d t="wgkm">20</d><d t="wgkt">11</d><d t="mslp">1015.0</d><d t="r9">0.2</d></obs><obs obs-time-local="20160319T1530" obs-time-utc="20160319T0430" time-zone="EDT" site ="092045" wmo="94983" station="Eddystone Pt" source="METAR" locale-type="locality" locale-num="" locale=""><d t="at">17.5</d><d t="dp">9.4</d><d t="rh">59</d><d t="wd">S</d><d t="wskm">46</d><d t="wskt">25</d><d t="wgkm">57</d><d t="wgkt">31</d><d t="mslp">1013.6</d><d t="r9">0.0</d></obs><obs obs-time-local="20160319T1530" obs-time-utc="20160319T0430" time-zone="EDT" site ="092012" wmo="95974" station="Fingal" source="METAR" locale-type="locality" locale-num="" locale=""><d t="at">15.1</d><d t="dp">3.3</d><d t="rh">45</d><d t="wd">SW</d><d t="wskm">13</d><d t="wskt">7</d><d t="wgkm">20</d><d t="wgkt">11</d><d t="r9">0.0</d></obs><obs obs-time-local="20160319T1530" obs-time-utc="20160319T0430" time-zone="EDT" site ="099005" wmo="94980" station="Flinders Island" source="METAR" locale-type="locality" locale-num="" locale=""><d t="at">17.7</d><d t="dp">8.0</d><d t="rh">53</d><d t="wd">SSW</d><d t="wskm">18</d><d t="wskt">10</d><d t="wgkm">26</d><d t="wgkt">14</d><d t="mslp">1014.2</d><d t="r9">0.0</d></obs><obs obs-time-local="20160319T1534" obs-time-utc="20160319T0434" time-zone="EDT" site ="092114" wmo="94987" station="Friendly Beaches" source="METAR" locale-type="locality" locale-num="" locale=""><d t="at">15.9</d><d t="dp">6.1</d><d t="rh">52</d><d t="wd">SSW</d><d t="wskm">30</d><d t="wskt">16</d><d t="wgkm">48</d><d t="wgkt">26</d><d t="mslp">1014.8</d><d t="r9">0.0</d></obs><obs obs-time-local="20160319T1530" obs-time-utc="20160319T0430" time-zone="EDT" site ="094191" wmo="94977" station="Hartz Mts" source="METAR" locale-type="locality" locale-num="" locale=""><d t="at">6.1</d><d t="dp">2.2</d><d t="rh">76</d><d t="wd">SSW</d><d t="wskm">20</d><d t="wskt">11</d><d t="wgkm">35</d><d t="wgkt">19</d><d t="r9">0.2</d></obs><obs obs-time-local="20160319T1530" obs-time-utc="20160319T0430" time-zone="EDT" site ="094029" wmo="94970" station="Hobart" source="METAR" locale-type="locality" locale-num="" locale=""><d t="at">14.7</d><d t="dp">1.7</d><d t="rh">41</d><d t="wd">SSW</d><d t="wskm">20</d><d t="wskt">11</d><d t="wgkm">30</d><d t="wgkt">16</d><d t="mslp">1016.4</d><d t="r9">0.2</d></obs><obs obs-time-local="20160319T1530" obs-time-utc="20160319T0430" time-zone="EDT" site ="094008" wmo="94975" station="Hobart Airport" source="METAR" locale-type="locality" locale-num="" locale=""><d t="at">14.2</d><d t="dp">3.0</d><d t="rh">47</d><d t="wd">SSW</d><d t="wskm">22</d><d t="wskt">12</d><d t="wgkm">30</d><d t="wgkt">16</d><d t="mslp">1016.4</d><d t="r9">0.8</d></obs><obs obs-time-local="20160319T1530" obs-time-utc="20160319T0430" time-zone="EDT" site ="000000" wmo="94949" station="Hogan Is" source="METAR" locale-type="locality" locale-num="" locale=""><d t="at">17.0</d><d t="dp">5.9</d><d t="rh">48</d><d t="wd">SSW</d><d t="wskm">22</d><d t="wskt">12</d><d t="wgkm">31</d><d t="wgkt">17</d><d t="mslp">1015.4</d><d t="r9">0.0</d></obs><obs obs-time-local="20160319T1530" obs-time-utc="20160319T0430" time-zone="EDT" site ="098017" wmo="94850" station="King Is Airport" source="METAR" locale-type="locality" locale-num="" locale=""><d t="at">16.2</d><d t="dp">5.5</d><d t="rh">49</d><d t="wd">SSW</d><d t="wskm">26</d><d t="wskt">14</d><d t="wgkm">37</d><d t="wgkt">20</d><d t="mslp">1018.1</d><d t="r9">0.0</d></obs><obs obs-time-local="20160319T1530" obs-time-utc="20160319T0430" time-zone="EDT" site ="091237" wmo="94969" station="Launceston" source="METAR" locale-type="locality" locale-num="" locale=""><d t="at">17.4</d><d t="dp">5.4</d><d t="rh">45</d><d t="wd">SE</d><d t="wskm">15</d><d t="wskt">8</d><d t="wgkm">24</d><d t="wgkt">13</d><d t="r9">0.0</d></obs><obs obs-time-local="20160319T1530" obs-time-utc="20160319T0430" time-zone="EDT" site ="091311" wmo="95966" station="Launceston Airport" source="METAR" locale-type="locality" locale-num="" locale=""><d t="at">16.1</d><d t="dp">3.9</d><d t="rh">44</d><d t="wd">SE</d><d t="wskm">20</d><d t="wskt">11</d><d t="wgkm">30</d><d t="wgkt">16</d><d t="mslp">1015.0</d><d t="r9">0.0</d></obs><obs obs-time-local="20160319T1530" obs-time-utc="20160319T0430" time-zone="EDT" site ="096033" wmo="95959" station="Liawenee" source="METAR" locale-type="locality" locale-num="" locale=""><d t="at">8.4</d><d t="dp">2.8</d><d t="rh">68</d><d t="wd">S</d><d t="wskm">20</d><d t="wskt">11</d><d t="wgkm">28</d><d t="wgkt">15</d><d t="mslp">1015.2</d><d t="r9">0.2</d></obs><obs obs-time-local="20160319T1530" obs-time-utc="20160319T0430" time-zone="EDT" site ="091293" wmo="95964" station="Low Head" source="METAR" locale-type="locality" locale-num="" locale=""><d t="at">18.2</d><d t="dp">4.7</d><d t="rh">41</d><d t="wd">SSE</d><d t="wskm">18</d><d t="wskt">10</d><d t="wgkm">30</d><d t="wgkt">16</d><d t="mslp">1014.6</d><d t="r9">0.0</d></obs><obs obs-time-local="20160319T1500" obs-time-utc="20160319T0400" time-zone="EDT" site ="097080" wmo="95961" station="Low Rocky Pt" source="SYNOP" locale-type="locality" locale-num="" locale=""><d t="at">15.7</d><d t="dp">5.9</d><d t="rh">52</d><d t="wd">S</d><d t="wskm">26</d><d t="wskt">14</d><d t="mslp">1017.7</d><d t="r9">0.0</d></obs><obs obs-time-local="20160319T1530" obs-time-utc="20160319T0430" time-zone="EDT" site ="091259" wmo="95956" station="Luncheon Hill" source="METAR" locale-type="locality" locale-num="" locale=""><d t="at">12.6</d><d t="dp">5.1</d><d t="rh">60</d><d t="wd">S</d><d t="wskm">26</d><d t="wskt">14</d><d t="wgkm">44</d><d t="wgkt">24</d><d t="r9">0.0</d></obs><obs obs-time-local="20160319T1530" obs-time-utc="20160319T0430" time-zone="EDT" site ="094041" wmo="94962" station="Maatsuyker Is" source="METAR" locale-type="locality" locale-num="" locale=""><d t="at">11.6</d><d t="dp">3.8</d><d t="rh">59</d><d t="wd">SSW</d><d t="wskm">28</d><d t="wskt">15</d><d t="wgkm">35</d><d t="wgkt">19</d><d t="mslp">1017.7</d><d t="r9">0.0</d></obs><obs obs-time-local="20160319T1530" obs-time-utc="20160319T0430" time-zone="EDT" site ="300004" wmo="94998" station="Macquarie Island" source="METAR" locale-type="locality" locale-num="" locale=""><d t="at">6.4</d><d t="dp">1.7</d><d t="rh">72</d><d t="wd">W</d><d t="wskm">35</d><d t="wskt">19</d><d t="wgkm">43</d><d t="wgkt">23</d><d t="mslp">1004.7</d><d t="r9">0.0</d></obs><obs obs-time-local="20160319T1530" obs-time-utc="20160319T0430" time-zone="EDT" site ="092124" wmo="95988" station="Maria Island" source="METAR" locale-type="locality" locale-num="" locale=""><d t="at">13.8</d><d t="wd">SSW</d><d t="wskm">39</d><d t="wskt">21</d><d t="wgkm">52</d><d t="wgkt">28</d><d t="mslp">1015.1</d><d t="r9">0.0</d></obs><obs obs-time-local="20160319T1500" obs-time-utc="20160319T0400" time-zone="EDT" site ="095063" wmo="94963" station="Maydena" source="SYNOP" locale-type="locality" locale-num="" locale=""><d t="at">12.6</d><d t="dp">5.0</d><d t="rh">60</d><d t="wd">SW</d><d t="wskm">22</d><d t="wskt">12</d><d t="r9">0.2</d></obs><obs obs-time-local="20160319T1500" obs-time-utc="20160319T0400" time-zone="EDT" site ="097085" wmo="95952" station="Mount Read" source="SYNOP" locale-type="locality" locale-num="" locale=""><d t="at">6.2</d><d t="dp">6.2</d><d t="rh">100</d><d t="wd">S</d><d t="wskm">26</d><d t="wskt">14</d><d t="mslp">1014.5</d><d t="r9">0.0</d></obs><obs obs-time-local="20160319T1530" obs-time-utc="20160319T0430" time-zone="EDT" site ="094087" wmo="95979" station="Mt Wellington" source="METAR" locale-type="locality" locale-num="" locale=""><d t="at">3.9</d><d t="dp">0.9</d><d t="rh">81</d><d t="wd">SSW</d><d t="wskm">24</d><d t="wskt">13</d><d t="wgkm">35</d><d t="wgkt">19</d><d t="r9">0.6</d></obs><obs obs-time-local="20160319T1530" obs-time-utc="20160319T0430" time-zone="EDT" site ="095048" wmo="94957" station="Ouse" source="METAR" locale-type="locality" locale-num="" locale=""><d t="at">15.8</d><d t="dp">3.3</d><d t="rh">43</d><d t="wd">S</d><d t="wskm">15</d><d t="wskt">8</d><d t="wgkm">20</d><d t="wgkt">11</d><d t="mslp">1015.8</d><d t="r9">0.0</d></obs><obs obs-time-local="20160319T1530" obs-time-utc="20160319T0430" time-zone="EDT" site ="097083" wmo="95958" station="Scotts Peak" source="METAR" locale-type="locality" locale-num="" locale=""><d t="at">12.0</d><d t="dp">5.4</d><d t="rh">64</d><d t="wd">WSW</d><d t="wskm">22</d><d t="wskt">12</d><d t="wgkm">31</d><d t="wgkt">17</d><d t="r9">0.0</d></obs><obs obs-time-local="20160319T1530" obs-time-utc="20160319T0430" time-zone="EDT" site ="091219" wmo="94972" station="Scottsdale" source="METAR" locale-type="locality" locale-num="" locale=""><d t="at">16.2</d><d t="dp">2.3</d><d t="rh">39</d><d t="wd">SSW</d><d t="wskm">26</d><d t="wskt">14</d><d t="wgkm">41</d><d t="wgkt">22</d><d t="mslp">1014.0</d><d t="r9">0.0</d></obs><obs obs-time-local="20160319T1500" obs-time-utc="20160319T0400" time-zone="EDT" site ="091291" wmo="94955" station="Sheffield" source="SYNOP" locale-type="locality" locale-num="" locale=""><d t="at">15.8</d><d t="dp">2.6</d><d t="rh">41</d><d t="wd">SE</d><d t="wskm">4</d><d t="wskt">2</d><d t="mslp">1014.2</d><d t="r9">0.0</d></obs><obs obs-time-local="20160319T1530" obs-time-utc="20160319T0430" time-zone="EDT" site ="091292" wmo="94953" station="Smithton" source="METAR" locale-type="locality" locale-num="" locale=""><d t="at">17.0</d><d t="dp">7.1</d><d t="rh">52</d><d t="wd">SSW</d><d t="wskm">30</d><d t="wskt">16</d><d t="wgkm">39</d><d t="wgkt">21</d><d t="mslp">1016.2</d><d t="r9">0.0</d></obs><obs obs-time-local="20160319T1530" obs-time-utc="20160319T0430" time-zone="EDT" site ="092120" wmo="95981" station="St Helens" source="METAR" locale-type="locality" locale-num="" locale=""><d t="at">16.1</d><d t="dp">8.6</d><d t="rh">61</d><d t="wd">SSE</d><d t="wskm">17</d><d t="wskt">9</d><d t="wgkm">30</d><d t="wgkt">16</d><d t="mslp">1014.3</d><d t="r9">0.0</d></obs><obs obs-time-local="20160319T1530" obs-time-utc="20160319T0430" time-zone="EDT" site ="097072" wmo="94956" station="Strahan AP" source="METAR" locale-type="locality" locale-num="" locale=""><d t="at">15.1</d><d t="dp">5.3</d><d t="rh">52</d><d t="wd">S</d><d t="wskm">22</d><d t="wskt">12</d><d t="wgkm">31</d><d t="wgkt">17</d><d t="mslp">1017.4</d><d t="r9">0.2</d></obs><obs obs-time-local="20160319T1530" obs-time-utc="20160319T0430" time-zone="EDT" site ="092123" wmo="95985" station="Swan Is" source="METAR" locale-type="locality" locale-num="" locale=""><d t="at">19.1</d><d t="dp">7.2</d><d t="rh">46</d><d t="wd">SSE</d><d t="wskm">15</d><d t="wskt">8</d><d t="wgkm">22</d><d t="wgkt">12</d><d t="mslp">1013.8</d><d t="r9">0.0</d></obs><obs obs-time-local="20160319T1530" obs-time-utc="20160319T0430" time-zone="EDT" site ="094155" wmo="95986" station="Tasman Is" source="METAR" locale-type="locality" locale-num="" locale=""><d t="at">11.8</d><d t="dp">4.5</d><d t="rh">61</d><d t="wd">SSW</d><d t="wskm">31</d><d t="wskt">17</d><d t="wgkm">50</d><d t="wgkt">27</d><d t="mslp">1015.3</d><d t="r9">0.0</d></obs><obs obs-time-local="20160319T1530" obs-time-utc="20160319T0430" time-zone="EDT" site ="094195" wmo="94960" station="Tunnack" source="METAR" locale-type="locality" locale-num="" locale=""><d t="at">12.4</d><d t="dp">2.0</d><d t="rh">49</d><d t="wd">SSW</d><d t="wskm">18</d><d t="wskt">10</d><d t="wgkm">28</d><d t="wgkt">15</d><d t="mslp">1015.6</d><d t="r9">0.0</d></obs><obs obs-time-local="20160319T1530" obs-time-utc="20160319T0430" time-zone="EDT" site ="097024" wmo="95962" station="Warra" source="METAR" locale-type="locality" locale-num="" locale=""><d t="at">9.9</d><d t="dp">4.3</d><d t="rh">68</d><d t="wd">SSW</d><d t="wskm">6</d><d t="wskt">3</d><d t="wgkm">13</d><d t="wgkt">7</d><d t="r9">0.0</d></obs><obs obs-time-local="20160319T1530" obs-time-utc="20160319T0430" time-zone="EDT" site ="091107" wmo="95957" station="Wynyard" source="METAR" locale-type="locality" locale-num="" locale=""><d t="at">17.9</d><d t="dp">3.0</d><d t="rh">37</d><d t="wd">SSW</d><d t="wskm">9</d><d t="wskt">5</d><d t="wgkm">17</d><d t="wgkt">9</d><d t="mslp">1014.9</d><d t="r9">0.0</d></obs></group></product></weather-observations>
